elastic_blast/__init__.py
elastic_blast/aws.py
elastic_blast/aws_traits.py
elastic_blast/base.py
elastic_blast/config.py
elastic_blast/constants.py
elastic_blast/cost.py
elastic_blast/db_metadata.py
elastic_blast/elasticblast.py
elastic_blast/elasticblast_factory.py
elastic_blast/elb_config.py
elastic_blast/filehelper.py
elastic_blast/gcp.py
elastic_blast/gcp_traits.py
elastic_blast/janitor.py
elastic_blast/jobs.py
elastic_blast/kubernetes.py
elastic_blast/object_storage_utils.py
elastic_blast/split.py
elastic_blast/subst.py
elastic_blast/taxonomy.py
elastic_blast/tuner.py
elastic_blast/util.py
elastic_blast/commands/__init__.py
elastic_blast/commands/delete.py
elastic_blast/commands/run_summary.py
elastic_blast/commands/status.py
elastic_blast/commands/submit.py
elastic_blast/resources/__init__.py
elastic_blast/resources/quotas/__init__.py
elastic_blast/resources/quotas/quota_aws_batch.py
elastic_blast/resources/quotas/quota_aws_ec2_cf.py
elastic_blast/resources/quotas/quota_check.py
elastic_blast/templates/blast-batch-job-local-ssd.yaml.template
elastic_blast/templates/blast-batch-job.yaml.template
elastic_blast/templates/cloudformation-admin-iam.yaml
elastic_blast/templates/elastic-blast-cf.yaml
elastic_blast/templates/elastic-blast-janitor-cf.yaml
elastic_blast/templates/elb-janitor-cronjob.yaml.template
elastic_blast/templates/elb-janitor-rbac.yaml
elastic_blast/templates/job-cloud-split-local-ssd.yaml.template
elastic_blast/templates/job-init-local-ssd.yaml.template
elastic_blast/templates/job-init-pv.yaml.template
elastic_blast/templates/job-submit-jobs.yaml.template
elastic_blast/templates/pvc-rom.yaml.template
elastic_blast/templates/pvc-rwo.yaml.template
elastic_blast/templates/storage-gcp-ssd.yaml
elastic_blast/templates/storage-gcp.yaml
elastic_blast/templates/volume-snapshot-class.yaml
elastic_blast/templates/volume-snapshot.yaml
elastic_blast-1.4.0.data/data/Makefile/Makefile
elastic_blast-1.4.0.data/data/share/doc/CloudJobSubmission.drawio
elastic_blast-1.4.0.dist-info/METADATA
elastic_blast-1.4.0.dist-info/WHEEL
elastic_blast-1.4.0.dist-info/top_level.txt
elastic_blast-1.4.0.dist-info/RECORD
